TLS/__init__.py
TLS/main.py
Temp_Linux_Shell-1.0.dist-info/LICENSE
Temp_Linux_Shell-1.0.dist-info/METADATA
Temp_Linux_Shell-1.0.dist-info/WHEEL
Temp_Linux_Shell-1.0.dist-info/entry_points.txt
Temp_Linux_Shell-1.0.dist-info/top_level.txt
Temp_Linux_Shell-1.0.dist-info/RECORD
