Metadata-Version: 2.1
Name: Temp-Linux-Shell
Version: 1.0
Summary: Wrapper around Chroot to make it easy to use temporary Linux Shells.
Home-page: https://github.com/Noriskky/tls
Author: Noriskky
Author-email: Noriskky44@proton.me
License: GPLv3
Keywords: cli,tls,alpine,temp-system,temp-linux-shell,temp-linux-system
Platform: Linux
Classifier: Programming Language :: Python :: 3
Classifier: License :: OSI Approved :: GNU General Public License v3 (GPLv3)
Classifier: Operating System :: POSIX :: Linux
Requires-Python: >=3.6
License-File: LICENSE
Requires-Dist: requests
Requires-Dist: tqdm
